odoo10_addon_storage_media_product-10.0.2.0.1-py3.8-nspkg.pth
odoo/addons/storage_media_product/README.rst
odoo/addons/storage_media_product/__init__.py
odoo/addons/storage_media_product/__manifest__.py
odoo/addons/storage_media_product/i18n/storage_media_product.pot
odoo/addons/storage_media_product/models/__init__.py
odoo/addons/storage_media_product/models/product.py
odoo/addons/storage_media_product/models/product_category.py
odoo/addons/storage_media_product/security/ir.model.access.csv
odoo/addons/storage_media_product/static/description/icon.png
odoo/addons/storage_media_product/views/product.xml
odoo/addons/storage_media_product/views/product_category.xml
odoo10_addon_storage_media_product-10.0.2.0.1.dist-info/METADATA
odoo10_addon_storage_media_product-10.0.2.0.1.dist-info/WHEEL
odoo10_addon_storage_media_product-10.0.2.0.1.dist-info/namespace_packages.txt
odoo10_addon_storage_media_product-10.0.2.0.1.dist-info/top_level.txt
odoo10_addon_storage_media_product-10.0.2.0.1.dist-info/RECORD
